tgpm/__init__.py
tgpm/exc.py
tgpm/model_permission_generator.py
tgpm/permission_adder.py
tgpm/permission_validator.py
tgpm/registry.py
tgpm/tgpm.py
tgpm/resource_permission/__init__.py
tgpm/resource_permission/repository.py
tgpm/resource_permission/statement_generator.py
tgpm-0.2.0.dist-info/LICENSE
tgpm-0.2.0.dist-info/METADATA
tgpm-0.2.0.dist-info/WHEEL
tgpm-0.2.0.dist-info/top_level.txt
tgpm-0.2.0.dist-info/RECORD
