Metadata-Version: 2.1
Name: tgpm
Version: 0.2.0
Author-email: Baboin Arthur <baboin.arthur@gmail.com>
Project-URL: Homepage, https://gitlab.com/Tagashy/tgpm
Project-URL: Documentation, https://tagashy.gitlab.io/tgpm/
Project-URL: Repository, https://gitlab.com/Tagashy/tgpm.git
Project-URL: Issues, https://gitlab.com/Tagashy/tgpm/issues
Project-URL: Bug Tracker, https://gitlab.com/Tagashy/tgpm/issues
Classifier: Development Status :: 3 - Alpha
Classifier: Intended Audience :: Developers
Classifier: Topic :: Software Development :: Code Generators
Classifier: Topic :: Software Development :: Libraries
Classifier: Programming Language :: Python :: 3.12
Classifier: License :: OSI Approved :: MIT License
Classifier: Operating System :: OS Independent
Requires-Python: >=3.12
License-File: LICENSE
Requires-Dist: sqlalchemy ~=2.0.28
Requires-Dist: sql-repository-generator ~=1.1.0
Provides-Extra: tests
Requires-Dist: pytest ~=8.0.2 ; extra == 'tests'
Requires-Dist: pytest-mock ~=3.12.0 ; extra == 'tests'
Requires-Dist: pytest-cov ~=4.1.0 ; extra == 'tests'
Requires-Dist: pytest-asyncio ~=0.23.2 ; extra == 'tests'
Requires-Dist: pytest-unordered ~=0.5.2 ; extra == 'tests'
Requires-Dist: gevent ~=24.2.1 ; extra == 'tests'
Requires-Dist: aiosqlite ==0.19.0 ; extra == 'tests'
Requires-Dist: EasyFactory ~=1.3.0 ; extra == 'tests'
